pyConfigFiles/__init__.py
pyConfigFiles/core.py
pyConfigFiles-0.0.13.dist-info/METADATA
pyConfigFiles-0.0.13.dist-info/WHEEL
pyConfigFiles-0.0.13.dist-info/entry_points.txt
pyConfigFiles-0.0.13.dist-info/top_level.txt
pyConfigFiles-0.0.13.dist-info/RECORD
