Metadata-Version: 2.1
Name: pyConfigFiles
Version: 0.0.13
Home-page: https://github.com/RPeschke/PyConfigFiles
Author: Richard Peschke
Author-email: peschke@hawaii.edu
Classifier: Programming Language :: Python :: 3
Classifier: License :: OSI Approved :: MIT License
Classifier: Operating System :: OS Independent
Requires-Python: >=3.8
